BranchedGP/BranchingTree.py
BranchedGP/FitBranchingModel.py
BranchedGP/VBHelperFunctions.py
BranchedGP/__init__.py
BranchedGP/assigngp_dense.py
BranchedGP/assigngp_denseSparse.py
BranchedGP/branch_kernParamGPflow.py
BranchedGP/pZ_construction_singleBP.py
BranchedGP-2.0.dist-info/LICENSE
BranchedGP-2.0.dist-info/METADATA
BranchedGP-2.0.dist-info/WHEEL
BranchedGP-2.0.dist-info/top_level.txt
BranchedGP-2.0.dist-info/RECORD
