Metadata-Version: 2.1
Name: BranchedGP
Version: 2.0
Summary: Branching Gaussian process.
Home-page: https://github.com/ManchesterBioinference/BranchedGP
Author: Alexis Boukouvalas
Author-email: alexis.boukouvalas@gmail.com
Maintainer: Alexis Boukouvalas
Maintainer-email: alexis.boukouvalas@gmail.com
License: MIT
Download-URL: https://github.com/ManchesterBioinference/BranchedGP
Platform: UNKNOWN
Requires-Python: >=3.5
Requires-Dist: tensorflow (<3,>=2)
Requires-Dist: gpflow (<3,>=2)
Requires-Dist: matplotlib
